better_selenium/__init__.py
better_selenium/browser.py
better_selenium-1.4.dist-info/LICENSE
better_selenium-1.4.dist-info/METADATA
better_selenium-1.4.dist-info/WHEEL
better_selenium-1.4.dist-info/top_level.txt
better_selenium-1.4.dist-info/RECORD
