Metadata-Version: 2.1
Name: better-selenium
Version: 1.4
Summary: A better selenium class with more features.
Author-email: Izaan Noman <pythonlogstest@gmail.com>
Project-URL: Homepage, https://github.com/pypa/sampleproject
Project-URL: Bug Tracker, https://github.com/pypa/sampleproject/issues
Classifier: Programming Language :: Python :: 3
Classifier: License :: OSI Approved :: MIT License
Classifier: Operating System :: OS Independent
Requires-Python: >=3.7
License-File: LICENSE
Requires-Dist: selenium >=4.14.0
